{
  "appeal": 2,
  "flavor_text_entries": [
    {
      "flavor_text": "Earn +2 if the Pok\u00e9mon performs last in the turn.",
      "language": {
        "name": "en",
        "url": "https://pokeapi.co/api/v2/language/9/"
      }
    }
  ],
  "id": 18,
  "moves": [
    {
      "name": "mega-punch",
      "url": "https://pokeapi.co/api/v2/move/5/"
    },
    {
      "name": "mega-kick",
      "url": "https://pokeapi.co/api/v2/move/25/"
    },
    {
      "name": "earthquake",
      "url": "https://pokeapi.co/api/v2/move/89/"
    },
    {
      "name": "sludge",
      "url": "https://pokeapi.co/api/v2/move/124/"
    },
    {
      "name": "crabhammer",
      "url": "https://pokeapi.co/api/v2/move/152/"
    },
    {
      "name": "hyper-fang",
      "url": "https://pokeapi.co/api/v2/move/158/"
    },
    {
      "name": "feint-attack",
      "url": "https://pokeapi.co/api/v2/move/185/"
    },
    {
      "name": "sludge-bomb",
      "url": "https://pokeapi.co/api/v2/move/188/"
    },
    {
      "name": "frustration",
      "url": "https://pokeapi.co/api/v2/move/218/"
    },
    {
      "name": "magnitude",
      "url": "https://pokeapi.co/api/v2/move/222/"
    },
    {
      "name": "dynamic-punch",
      "url": "https://pokeapi.co/api/v2/move/223/"
    },
    {
      "name": "megahorn",
      "url": "https://pokeapi.co/api/v2/move/224/"
    },
    {
      "name": "iron-tail",
      "url": "https://pokeapi.co/api/v2/move/231/"
    },
    {
      "name": "metal-claw",
      "url": "https://pokeapi.co/api/v2/move/232/"
    },
    {
      "name": "cross-chop",
      "url": "https://pokeapi.co/api/v2/move/238/"
    },
    {
      "name": "crunch",
      "url": "https://pokeapi.co/api/v2/move/242/"
    },
    {
      "name": "ancient-power",
      "url": "https://pokeapi.co/api/v2/move/246/"
    },
    {
      "name": "rock-smash",
      "url": "https://pokeapi.co/api/v2/move/249/"
    },
    {
      "name": "spit-up",
      "url": "https://pokeapi.co/api/v2/move/255/"
    },
    {
      "name": "superpower",
      "url": "https://pokeapi.co/api/v2/move/276/"
    },
    {
      "name": "eruption",
      "url": "https://pokeapi.co/api/v2/move/284/"
    },
    {
      "name": "meteor-mash",
      "url": "https://pokeapi.co/api/v2/move/309/"
    },
    {
      "name": "muddy-water",
      "url": "https://pokeapi.co/api/v2/move/330/"
    },
    {
      "name": "natural-gift",
      "url": "https://pokeapi.co/api/v2/move/363/"
    },
    {
      "name": "force-palm",
      "url": "https://pokeapi.co/api/v2/move/395/"
    },
    {
      "name": "dragon-rush",
      "url": "https://pokeapi.co/api/v2/move/407/"
    },
    {
      "name": "brave-bird",
      "url": "https://pokeapi.co/api/v2/move/413/"
    },
    {
      "name": "earth-power",
      "url": "https://pokeapi.co/api/v2/move/414/"
    },
    {
      "name": "mud-bomb",
      "url": "https://pokeapi.co/api/v2/move/426/"
    },
    {
      "name": "zen-headbutt",
      "url": "https://pokeapi.co/api/v2/move/428/"
    },
    {
      "name": "rock-climb",
      "url": "https://pokeapi.co/api/v2/move/431/"
    },
    {
      "name": "iron-head",
      "url": "https://pokeapi.co/api/v2/move/442/"
    },
    {
      "name": "wood-hammer",
      "url": "https://pokeapi.co/api/v2/move/452/"
    }
  ]
}