{
  "areas": [
    {
      "name": "icepeak-cavern-area",
      "url": "https://pokeapi.co/api/v2/location-area/990/"
    }
  ],
  "game_indices": [],
  "id": 996,
  "name": "icepeak-cavern",
  "names": [
    {
      "language": {
        "name": "de",
        "url": "https://pokeapi.co/api/v2/language/6/"
      },
      "name": "Eisgipfelh\u00f6hle"
    },
    {
      "language": {
        "name": "en",
        "url": "https://pokeapi.co/api/v2/language/9/"
      },
      "name": "Icepeak Cavern"
    }
  ],
  "region": {
    "name": "hisui",
    "url": "https://pokeapi.co/api/v2/region/9/"
  }
}